data/__init__.py
data/data-loading-notes.md
data/load_buildings.py
data/load_places.py
data/load_streets.py
data/pyarrow_test.ipynb
ebdptoolkit-0.0.1b0.dist-info/METADATA
ebdptoolkit-0.0.1b0.dist-info/WHEEL
ebdptoolkit-0.0.1b0.dist-info/licenses/LICENSE
pre_processing/__init__.py
pre_processing/prepare_streets.py
ebdptoolkit-0.0.1b0.dist-info/RECORD
